<?xml version="1.0" encoding="UTF-8"?>
<metadata xml:lang="en"><Esri><CreaDate>20170706</CreaDate><CreaTime>15051100</CreaTime><ArcGISFormat>1.0</ArcGISFormat><SyncOnce>TRUE</SyncOnce><ModDate>20230616</ModDate><ModTime>150210</ModTime></Esri><toolbox name="Flightline" alias=""><arcToolboxHelpPath>c:\program files\arcgis\pro\Resources\Help\gp</arcToolboxHelpPath><toolsets/></toolbox><dataIdInfo><idCitation><resTitle>Flightline</resTitle></idCitation></dataIdInfo><distInfo><distributor><distorFormat><formatName>ArcToolbox Toolbox</formatName></distorFormat></distributor></distInfo></metadata>
